{
  "id": "9c4a746c-d2ea-41eb-9c48-ae050c4cb95b",
  "index": 2910,
  "period": 2,
  "timestamp": "00:44:13.000",
  "minute": 89,
  "second": 13,
  "type": {
    "id": 16,
    "name": "Shot"
  },
  "possession": 195,
  "possession_team": {
    "id": 765,
    "name": "Portland Thorns"
  },
  "play_pattern": {
    "id": 2,
    "name": "From Corner"
  },
  "team": {
    "id": 765,
    "name": "Portland Thorns"
  },
  "player": {
    "id": 4999,
    "name": "Lindsey Horan"
  },
  "position": {
    "id": 11,
    "name": "Left Defensive Midfield"
  },
  "location": [
    110.0,
    26.0
  ],
  "duration": 1.053,
  "related_events": [
    "054f808d-db42-4b16-8c88-f6a481ab6723"
  ],
  "shot": {
    "statsbomb_xg": 0.029591165,
    "end_location": [
      119.0,
      36.8,
      1.5
    ],
    "key_pass_id": "2d1134b8-dec6-48b6-80ec-ab007f599df1",
    "type": {
      "id": 87,
      "name": "Open Play"
    },
    "body_part": {
      "id": 38,
      "name": "Left Foot"
    },
    "technique": {
      "id": 95,
      "name": "Volley"
    },
    "outcome": {
      "id": 100,
      "name": "Saved"
    },
    "first_time": true,
    "freeze_frame": [
      {
        "location": [
          119.0,
          39.0
        ],
        "player": {
          "id": 5019,
          "name": "Michelle Betos"
        },
        "position": {
          "id": 1,
          "name": "Goalkeeper"
        },
        "teammate": false
      },
      {
        "location": [
          115.0,
          46.0
        ],
        "player": {
          "id": 5008,
          "name": "Kristen McNabb"
        },
        "position": {
          "id": 5,
          "name": "Left Center Back"
        },
        "teammate": false
      },
      {
        "location": [
          113.0,
          50.0
        ],
        "player": {
          "id": 5000,
          "name": "Steph Catley"
        },
        "position": {
          "id": 6,
          "name": "Left Back"
        },
        "teammate": false
      },
      {
        "location": [
          111.0,
          41.0
        ],
        "player": {
          "id": 4998,
          "name": "Rumi Utsugi"
        },
        "position": {
          "id": 15,
          "name": "Left Center Midfield"
        },
        "teammate": false
      },
      {
        "location": [
          109.0,
          35.0
        ],
        "player": {
          "id": 5014,
          "name": "Madeline Bauer"
        },
        "position": {
          "id": 3,
          "name": "Right Center Back"
        },
        "teammate": false
      },
      {
        "location": [
          112.0,
          45.0
        ],
        "player": {
          "id": 5003,
          "name": "Emily Sonnett"
        },
        "position": {
          "id": 4,
          "name": "Center Back"
        },
        "teammate": true
      },
      {
        "location": [
          113.0,
          41.0
        ],
        "player": {
          "id": 5020,
          "name": "Christine Sinclair"
        },
        "position": {
          "id": 19,
          "name": "Center Attacking Midfield"
        },
        "teammate": true
      },
      {
        "location": [
          113.0,
          37.0
        ],
        "player": {
          "id": 5007,
          "name": "Megan Oyster"
        },
        "position": {
          "id": 4,
          "name": "Center Back"
        },
        "teammate": false
      },
      {
        "location": [
          113.0,
          31.0
        ],
        "player": {
          "id": 5001,
          "name": "Allie Long"
        },
        "position": {
          "id": 13,
          "name": "Right Center Midfield"
        },
        "teammate": false
      },
      {
        "location": [
          109.0,
          29.0
        ],
        "player": {
          "id": 4997,
          "name": "Alyssa Kleiner"
        },
        "position": {
          "id": 2,
          "name": "Right Back"
        },
        "teammate": false
      },
      {
        "location": [
          106.0,
          32.0
        ],
        "player": {
          "id": 10408,
          "name": "Ana-Maria Crnogorcevic"
        },
        "position": {
          "id": 22,
          "name": "Right Center Forward"
        },
        "teammate": true
      }
    ]
  }
}