{
  "id": "e937cca2-892d-4f28-811a-e9189b27d97d",
  "index": 1369,
  "period": 1,
  "timestamp": "00:43:58.853",
  "minute": 43,
  "second": 58,
  "type": {
    "id": 16,
    "name": "Shot"
  },
  "possession": 94,
  "possession_team": {
    "id": 763,
    "name": "Sky Blue FC"
  },
  "play_pattern": {
    "id": 1,
    "name": "Regular Play"
  },
  "team": {
    "id": 763,
    "name": "Sky Blue FC"
  },
  "player": {
    "id": 4992,
    "name": "Janine Beckie"
  },
  "position": {
    "id": 19,
    "name": "Center Attacking Midfield"
  },
  "location": [
    96.0,
    33.0
  ],
  "duration": 0.148,
  "related_events": [
    "03ebc850-31a4-4972-b62b-8ae86f79433e",
    "8cba8cd1-3359-43a8-9305-54dd27941ddc"
  ],
  "shot": {
    "statsbomb_xg": 0.033386517,
    "end_location": [
      97.0,
      34.0
    ],
    "key_pass_id": "f7733edb-a0bb-45ac-9e99-f077d346578b",
    "type": {
      "id": 87,
      "name": "Open Play"
    },
    "body_part": {
      "id": 38,
      "name": "Left Foot"
    },
    "technique": {
      "id": 93,
      "name": "Normal"
    },
    "outcome": {
      "id": 96,
      "name": "Blocked"
    },
    "freeze_frame": [
      {
        "location": [
          84.0,
          25.0
        ],
        "player": {
          "id": 4973,
          "name": "Diana Matheson"
        },
        "position": {
          "id": 18,
          "name": "Right Attacking Midfield"
        },
        "teammate": false
      },
      {
        "location": [
          87.0,
          42.0
        ],
        "player": {
          "id": 4975,
          "name": "Gunnhildur Yrsa J\u00f3nsd\u00f3ttir"
        },
        "position": {
          "id": 13,
          "name": "Right Center Midfield"
        },
        "teammate": false
      },
      {
        "location": [
          93.0,
          35.0
        ],
        "player": {
          "id": 4979,
          "name": "Katrina Gorry"
        },
        "position": {
          "id": 19,
          "name": "Center Attacking Midfield"
        },
        "teammate": false
      },
      {
        "location": [
          83.0,
          34.0
        ],
        "player": {
          "id": 4989,
          "name": "Rebekah Stott"
        },
        "position": {
          "id": 6,
          "name": "Left Back"
        },
        "teammate": true
      },
      {
        "location": [
          96.0,
          57.0
        ],
        "player": {
          "id": 4968,
          "name": "Madison Tiernan"
        },
        "position": {
          "id": 17,
          "name": "Right Wing"
        },
        "teammate": true
      },
      {
        "location": [
          87.0,
          33.0
        ],
        "player": {
          "id": 4966,
          "name": "Desiree Scott"
        },
        "position": {
          "id": 15,
          "name": "Left Center Midfield"
        },
        "teammate": false
      },
      {
        "location": [
          100.0,
          47.0
        ],
        "player": {
          "id": 4971,
          "name": "Rebecca Moros"
        },
        "position": {
          "id": 6,
          "name": "Left Back"
        },
        "teammate": false
      },
      {
        "location": [
          99.0,
          33.0
        ],
        "player": {
          "id": 4987,
          "name": "Sydney Miramontez"
        },
        "position": {
          "id": 5,
          "name": "Left Center Back"
        },
        "teammate": false
      },
      {
        "location": [
          100.0,
          29.0
        ],
        "player": {
          "id": 4984,
          "name": "Rachel Corsie"
        },
        "position": {
          "id": 3,
          "name": "Right Center Back"
        },
        "teammate": false
      },
      {
        "location": [
          99.0,
          15.0
        ],
        "player": {
          "id": 4986,
          "name": "Shea Groom"
        },
        "position": {
          "id": 21,
          "name": "Left Wing"
        },
        "teammate": true
      },
      {
        "location": [
          95.0,
          22.0
        ],
        "player": {
          "id": 4982,
          "name": "Katlyn Johnson"
        },
        "position": {
          "id": 23,
          "name": "Center Forward"
        },
        "teammate": true
      },
      {
        "location": [
          101.0,
          23.0
        ],
        "player": {
          "id": 4983,
          "name": "Brooke Elby"
        },
        "position": {
          "id": 2,
          "name": "Right Back"
        },
        "teammate": false
      },
      {
        "location": [
          119.0,
          41.0
        ],
        "player": {
          "id": 4969,
          "name": "Nicole Barnhart"
        },
        "position": {
          "id": 1,
          "name": "Goalkeeper"
        },
        "teammate": false
      }
    ]
  }
}