{
  "id": "6b3baff2-d948-4e5c-9843-814ad05cd5dd",
  "index": 1478,
  "period": 1,
  "timestamp": "00:35:36.945",
  "minute": 35,
  "second": 36,
  "type": {
    "id": 16,
    "name": "Shot"
  },
  "possession": 71,
  "possession_team": {
    "id": 217,
    "name": "Barcelona"
  },
  "play_pattern": {
    "id": 1,
    "name": "Regular Play"
  },
  "team": {
    "id": 217,
    "name": "Barcelona"
  },
  "player": {
    "id": 5203,
    "name": "Sergio Busquets i Burgos"
  },
  "position": {
    "id": 10,
    "name": "Center Defensive Midfield"
  },
  "location": [
    92.7,
    37.6
  ],
  "duration": 0.139801,
  "related_events": [
    "b1bef8f9-9c04-4ab3-8687-5b9dfa1636d0",
    "b7aac328-c994-4219-b985-3d6838269d66"
  ],
  "shot": {
    "statsbomb_xg": 0.034480885,
    "end_location": [
      94.3,
      37.7
    ],
    "body_part": {
      "id": 38,
      "name": "Left Foot"
    },
    "type": {
      "id": 87,
      "name": "Open Play"
    },
    "outcome": {
      "id": 96,
      "name": "Blocked"
    },
    "first_time": true,
    "technique": {
      "id": 93,
      "name": "Normal"
    },
    "freeze_frame": [
      {
        "location": [
          94.8,
          37.6
        ],
        "player": {
          "id": 25881,
          "name": "Juan Antonio Rodr\u00edguez Villamuela"
        },
        "position": {
          "id": 11,
          "name": "Left Defensive Midfield"
        },
        "teammate": false
      },
      {
        "location": [
          94.5,
          42.6
        ],
        "player": {
          "id": 6998,
          "name": "Rafael Alc\u00e2ntara do Nascimento"
        },
        "position": {
          "id": 13,
          "name": "Right Center Midfield"
        },
        "teammate": true
      },
      {
        "location": [
          87.3,
          53.5
        ],
        "player": {
          "id": 4324,
          "name": "Daniel Alves da Silva"
        },
        "position": {
          "id": 2,
          "name": "Right Back"
        },
        "teammate": true
      },
      {
        "location": [
          99.0,
          33.4
        ],
        "player": {
          "id": 20131,
          "name": "Xavier Hern\u00e1ndez Creus"
        },
        "position": {
          "id": 15,
          "name": "Left Center Midfield"
        },
        "teammate": true
      },
      {
        "location": [
          115.5,
          39.4
        ],
        "player": {
          "id": 6625,
          "name": "Vicente Guaita Panadero"
        },
        "position": {
          "id": 1,
          "name": "Goalkeeper"
        },
        "teammate": false
      },
      {
        "location": [
          101.9,
          35.2
        ],
        "player": {
          "id": 24506,
          "name": "\u00c1lvaro Arroyo Mart\u00ednez"
        },
        "position": {
          "id": 2,
          "name": "Right Back"
        },
        "teammate": false
      },
      {
        "location": [
          97.5,
          48.9
        ],
        "player": {
          "id": 11813,
          "name": "Emiliano Buend\u00eda"
        },
        "position": {
          "id": 21,
          "name": "Left Wing"
        },
        "teammate": false
      },
      {
        "location": [
          101.5,
          44.9
        ],
        "player": {
          "id": 27054,
          "name": "Roberto Lago Soto"
        },
        "position": {
          "id": 6,
          "name": "Left Back"
        },
        "teammate": false
      },
      {
        "location": [
          100.0,
          41.2
        ],
        "player": {
          "id": 6745,
          "name": "Mehdi Lacen"
        },
        "position": {
          "id": 9,
          "name": "Right Defensive Midfield"
        },
        "teammate": false
      },
      {
        "location": [
          100.7,
          40.3
        ],
        "player": {
          "id": 6614,
          "name": "Alexis Ruano Delgado"
        },
        "position": {
          "id": 5,
          "name": "Left Center Back"
        },
        "teammate": false
      },
      {
        "location": [
          101.8,
          39.9
        ],
        "player": {
          "id": 17054,
          "name": "Emiliano Daniel Vel\u00e1zquez Maldonado"
        },
        "position": {
          "id": 3,
          "name": "Right Center Back"
        },
        "teammate": false
      },
      {
        "location": [
          103.4,
          40.7
        ],
        "player": {
          "id": 5503,
          "name": "Lionel Andr\u00e9s Messi Cuccittini"
        },
        "position": {
          "id": 17,
          "name": "Right Wing"
        },
        "teammate": true
      },
      {
        "location": [
          101.5,
          38.6
        ],
        "player": {
          "id": 4320,
          "name": "Neymar da Silva Santos Junior"
        },
        "position": {
          "id": 21,
          "name": "Left Wing"
        },
        "teammate": true
      },
      {
        "location": [
          102.8,
          30.7
        ],
        "player": {
          "id": 5246,
          "name": "Luis Alberto Su\u00e1rez D\u00edaz"
        },
        "position": {
          "id": 23,
          "name": "Center Forward"
        },
        "teammate": true
      },
      {
        "location": [
          101.7,
          28.0
        ],
        "player": {
          "id": 6907,
          "name": "Pedro Le\u00f3n S\u00e1nchez Gil"
        },
        "position": {
          "id": 17,
          "name": "Right Wing"
        },
        "teammate": false
      },
      {
        "location": [
          102.0,
          23.2
        ],
        "player": {
          "id": 22102,
          "name": "Adriano Correia Claro"
        },
        "position": {
          "id": 6,
          "name": "Left Back"
        },
        "teammate": true
      }
    ]
  }
}