{
  "id": "968fefc3-cd53-4060-a31e-79500a9dbccf",
  "index": 3328,
  "period": 2,
  "timestamp": "00:37:41.858",
  "minute": 82,
  "second": 41,
  "type": {
    "id": 16,
    "name": "Shot"
  },
  "possession": 226,
  "possession_team": {
    "id": 98,
    "name": "Blackburn Rovers"
  },
  "play_pattern": {
    "id": 2,
    "name": "From Corner"
  },
  "team": {
    "id": 98,
    "name": "Blackburn Rovers"
  },
  "player": {
    "id": 24766,
    "name": "Dwight Yorke"
  },
  "position": {
    "id": 24,
    "name": "Left Center Forward"
  },
  "location": [
    114.7,
    41.3
  ],
  "duration": 1.054037,
  "related_events": [
    "56774680-5ee9-466a-8928-257e6335a700"
  ],
  "shot": {
    "statsbomb_xg": 0.3279063,
    "end_location": [
      120.0,
      37.5,
      3.8
    ],
    "type": {
      "id": 87,
      "name": "Open Play"
    },
    "outcome": {
      "id": 98,
      "name": "Off T"
    },
    "first_time": true,
    "technique": {
      "id": 91,
      "name": "Half Volley"
    },
    "body_part": {
      "id": 40,
      "name": "Right Foot"
    },
    "freeze_frame": [
      {
        "location": [
          114.7,
          30.9
        ],
        "player": {
          "id": 40356,
          "name": "Craig Short"
        },
        "position": {
          "id": 5,
          "name": "Left Center Back"
        },
        "teammate": true
      },
      {
        "location": [
          113.5,
          29.8
        ],
        "player": {
          "id": 15516,
          "name": "Thierry Henry"
        },
        "position": {
          "id": 24,
          "name": "Left Center Forward"
        },
        "teammate": false
      },
      {
        "location": [
          119.4,
          42.4
        ],
        "player": {
          "id": 12529,
          "name": "Ashley Cole"
        },
        "position": {
          "id": 6,
          "name": "Left Back"
        },
        "teammate": false
      },
      {
        "location": [
          115.0,
          46.8
        ],
        "player": {
          "id": 26194,
          "name": "Pascal Cygan"
        },
        "position": {
          "id": 5,
          "name": "Left Center Back"
        },
        "teammate": false
      },
      {
        "location": [
          116.6,
          44.1
        ],
        "player": {
          "id": 40221,
          "name": "Gilberto Aparecido da Silva"
        },
        "position": {
          "id": 15,
          "name": "Left Center Midfield"
        },
        "teammate": false
      },
      {
        "location": [
          115.2,
          35.5
        ],
        "player": {
          "id": 15515,
          "name": "Patrick Vieira"
        },
        "position": {
          "id": 13,
          "name": "Right Center Midfield"
        },
        "teammate": false
      },
      {
        "location": [
          117.1,
          32.6
        ],
        "player": {
          "id": 19312,
          "name": "Robert Pir\u00e8s "
        },
        "position": {
          "id": 16,
          "name": "Left Midfield"
        },
        "teammate": false
      },
      {
        "location": [
          119.6,
          37.6
        ],
        "player": {
          "id": 20015,
          "name": "Jens Lehmann"
        },
        "position": {
          "id": 1,
          "name": "Goalkeeper"
        },
        "teammate": false
      },
      {
        "location": [
          113.3,
          42.9
        ],
        "player": {
          "id": 40355,
          "name": "Andy Todd"
        },
        "position": {
          "id": 3,
          "name": "Right Center Back"
        },
        "teammate": true
      },
      {
        "location": [
          113.7,
          44.8
        ],
        "player": {
          "id": 40357,
          "name": "Brett Emerton"
        },
        "position": {
          "id": 12,
          "name": "Right Midfield"
        },
        "teammate": true
      },
      {
        "location": [
          116.7,
          41.7
        ],
        "player": {
          "id": 24767,
          "name": "Andy Cole"
        },
        "position": {
          "id": 22,
          "name": "Right Center Forward"
        },
        "teammate": true
      },
      {
        "location": [
          119.5,
          36.9
        ],
        "player": {
          "id": 15754,
          "name": "Fredrik Ljungberg"
        },
        "position": {
          "id": 12,
          "name": "Right Midfield"
        },
        "teammate": false
      },
      {
        "location": [
          116.3,
          39.9
        ],
        "player": {
          "id": 15637,
          "name": "Sulzeer Jeremiah \"Sol\" Campbell"
        },
        "position": {
          "id": 3,
          "name": "Right Center Back"
        },
        "teammate": false
      },
      {
        "location": [
          112.9,
          39.6
        ],
        "player": {
          "id": 38412,
          "name": "Kolo Habib Tour\u00e9"
        },
        "position": {
          "id": 2,
          "name": "Right Back"
        },
        "teammate": false
      }
    ]
  }
}