{
  "id": "c4ea8eb8-e6c2-4be2-ab55-541df7c03fd4",
  "index": 673,
  "period": 1,
  "timestamp": "00:19:50.987",
  "minute": 19,
  "second": 50,
  "type": {
    "id": 16,
    "name": "Shot"
  },
  "possession": 48,
  "possession_team": {
    "id": 766,
    "name": "North Carolina Courage"
  },
  "play_pattern": {
    "id": 4,
    "name": "From Throw In"
  },
  "team": {
    "id": 766,
    "name": "North Carolina Courage"
  },
  "player": {
    "id": 5087,
    "name": "Samantha Mewis"
  },
  "position": {
    "id": 13,
    "name": "Right Center Midfield"
  },
  "location": [
    111.0,
    46.0
  ],
  "duration": 0.32,
  "related_events": [
    "1e933834-9b31-47d2-961a-ef2351b163cf",
    "7f7ceceb-d5e3-4352-abda-1458463b60ba"
  ],
  "shot": {
    "statsbomb_xg": 0.0484662,
    "end_location": [
      112.0,
      47.0
    ],
    "body_part": {
      "id": 40,
      "name": "Right Foot"
    },
    "type": {
      "id": 87,
      "name": "Open Play"
    },
    "technique": {
      "id": 93,
      "name": "Normal"
    },
    "outcome": {
      "id": 96,
      "name": "Blocked"
    },
    "freeze_frame": [
      {
        "location": [
          109.0,
          49.0
        ],
        "player": {
          "id": 5091,
          "name": "McCall Zerboni"
        },
        "position": {
          "id": 15,
          "name": "Left Center Midfield"
        },
        "teammate": true
      },
      {
        "location": [
          110.0,
          45.0
        ],
        "player": {
          "id": 4988,
          "name": "Sarah Killion"
        },
        "position": {
          "id": 10,
          "name": "Center Defensive Midfield"
        },
        "teammate": false
      },
      {
        "location": [
          109.0,
          70.0
        ],
        "player": {
          "id": 5034,
          "name": "Jessica McDonald"
        },
        "position": {
          "id": 22,
          "name": "Right Center Forward"
        },
        "teammate": true
      },
      {
        "location": [
          107.0,
          56.0
        ],
        "player": {
          "id": 5037,
          "name": "Abby Erceg"
        },
        "position": {
          "id": 5,
          "name": "Left Center Back"
        },
        "teammate": true
      },
      {
        "location": [
          110.0,
          56.0
        ],
        "player": {
          "id": 4970,
          "name": "Amanda Frisbie"
        },
        "position": {
          "id": 6,
          "name": "Left Back"
        },
        "teammate": false
      },
      {
        "location": [
          112.0,
          51.0
        ],
        "player": {
          "id": 5097,
          "name": "Carli Lloyd"
        },
        "position": {
          "id": 13,
          "name": "Right Center Midfield"
        },
        "teammate": false
      },
      {
        "location": [
          112.0,
          45.0
        ],
        "player": {
          "id": 4978,
          "name": "Dominique Richardson"
        },
        "position": {
          "id": 3,
          "name": "Right Center Back"
        },
        "teammate": false
      },
      {
        "location": [
          104.0,
          56.0
        ],
        "player": {
          "id": 4986,
          "name": "Shea Groom"
        },
        "position": {
          "id": 21,
          "name": "Left Wing"
        },
        "teammate": false
      },
      {
        "location": [
          109.0,
          46.0
        ],
        "player": {
          "id": 5096,
          "name": "Savannah McCaskill"
        },
        "position": {
          "id": 17,
          "name": "Right Wing"
        },
        "teammate": false
      },
      {
        "location": [
          115.0,
          42.0
        ],
        "player": {
          "id": 5088,
          "name": "Crystal Alyssia Dunn"
        },
        "position": {
          "id": 24,
          "name": "Left Center Forward"
        },
        "teammate": true
      },
      {
        "location": [
          115.0,
          41.0
        ],
        "player": {
          "id": 5098,
          "name": "Erica Skroski"
        },
        "position": {
          "id": 2,
          "name": "Right Back"
        },
        "teammate": false
      },
      {
        "location": [
          120.0,
          44.0
        ],
        "player": {
          "id": 4981,
          "name": "Kailen Sheridan"
        },
        "position": {
          "id": 1,
          "name": "Goalkeeper"
        },
        "teammate": false
      },
      {
        "location": [
          111.0,
          35.0
        ],
        "player": {
          "id": 5044,
          "name": "D\u00e9bora Cristiane de Oliveira"
        },
        "position": {
          "id": 12,
          "name": "Right Midfield"
        },
        "teammate": true
      },
      {
        "location": [
          113.0,
          35.0
        ],
        "player": {
          "id": 4980,
          "name": "Thaysa de Moraes Rosa Moreno"
        },
        "position": {
          "id": 15,
          "name": "Left Center Midfield"
        },
        "teammate": false
      }
    ]
  }
}