{
  "id": "a6fba043-8cab-43c8-aa24-d4b93abff1b0",
  "index": 1976,
  "period": 1,
  "timestamp": "00:41:51.346",
  "minute": 41,
  "second": 51,
  "type": {
    "id": 16,
    "name": "Shot"
  },
  "possession": 81,
  "possession_team": {
    "id": 217,
    "name": "Barcelona"
  },
  "play_pattern": {
    "id": 1,
    "name": "Regular Play"
  },
  "team": {
    "id": 217,
    "name": "Barcelona"
  },
  "player": {
    "id": 5246,
    "name": "Luis Alberto Su\u00e1rez D\u00edaz"
  },
  "position": {
    "id": 23,
    "name": "Center Forward"
  },
  "location": [
    110.2,
    50.0
  ],
  "duration": 0.1022,
  "related_events": [
    "e433178b-d794-4fe9-b390-b82dc224fa32"
  ],
  "shot": {
    "statsbomb_xg": 0.06054292,
    "end_location": [
      120.0,
      48.6,
      1.6
    ],
    "type": {
      "id": 87,
      "name": "Open Play"
    },
    "outcome": {
      "id": 98,
      "name": "Off T"
    },
    "technique": {
      "id": 93,
      "name": "Normal"
    },
    "body_part": {
      "id": 40,
      "name": "Right Foot"
    },
    "freeze_frame": [
      {
        "location": [
          119.0,
          59.4
        ],
        "player": {
          "id": 6379,
          "name": "Sergi Roberto Carnicer"
        },
        "position": {
          "id": 2,
          "name": "Right Back"
        },
        "teammate": true
      },
      {
        "location": [
          113.6,
          41.3
        ],
        "player": {
          "id": 4320,
          "name": "Neymar da Silva Santos Junior"
        },
        "position": {
          "id": 21,
          "name": "Left Wing"
        },
        "teammate": true
      },
      {
        "location": [
          100.4,
          57.6
        ],
        "player": {
          "id": 5470,
          "name": "Ivan Rakiti\u0107"
        },
        "position": {
          "id": 13,
          "name": "Right Center Midfield"
        },
        "teammate": true
      },
      {
        "location": [
          96.4,
          47.7
        ],
        "player": {
          "id": 5216,
          "name": "Andr\u00e9s Iniesta Luj\u00e1n"
        },
        "position": {
          "id": 15,
          "name": "Left Center Midfield"
        },
        "teammate": true
      },
      {
        "location": [
          107.8,
          39.1
        ],
        "player": {
          "id": 5503,
          "name": "Lionel Andr\u00e9s Messi Cuccittini"
        },
        "position": {
          "id": 17,
          "name": "Right Wing"
        },
        "teammate": true
      },
      {
        "location": [
          116.3,
          57.0
        ],
        "player": {
          "id": 6828,
          "name": "Jaume Vicent Costa Jord\u00e1"
        },
        "position": {
          "id": 6,
          "name": "Left Back"
        },
        "teammate": false
      },
      {
        "location": [
          104.7,
          58.1
        ],
        "player": {
          "id": 6771,
          "name": "Manuel Trigueros Mu\u00f1oz"
        },
        "position": {
          "id": 9,
          "name": "Right Defensive Midfield"
        },
        "teammate": false
      },
      {
        "location": [
          95.7,
          58.0
        ],
        "player": {
          "id": 6759,
          "name": "Roberto Soriano"
        },
        "position": {
          "id": 16,
          "name": "Left Midfield"
        },
        "teammate": false
      },
      {
        "location": [
          97.7,
          30.4
        ],
        "player": {
          "id": 6357,
          "name": "Jonathan dos Santos Ram\u00edrez"
        },
        "position": {
          "id": 12,
          "name": "Right Midfield"
        },
        "teammate": false
      },
      {
        "location": [
          94.8,
          46.0
        ],
        "player": {
          "id": 6862,
          "name": "C\u00e9dric Bakambu"
        },
        "position": {
          "id": 22,
          "name": "Right Center Forward"
        },
        "teammate": false
      },
      {
        "location": [
          111.8,
          37.5
        ],
        "player": {
          "id": 6772,
          "name": "Mario Gaspar P\u00e9rez Mart\u00ednez"
        },
        "position": {
          "id": 2,
          "name": "Right Back"
        },
        "teammate": false
      },
      {
        "location": [
          108.9,
          43.2
        ],
        "player": {
          "id": 6765,
          "name": "Rodrigo Hern\u00e1ndez Cascante"
        },
        "position": {
          "id": 11,
          "name": "Left Defensive Midfield"
        },
        "teammate": false
      },
      {
        "location": [
          113.0,
          43.1
        ],
        "player": {
          "id": 7034,
          "name": "Mateo Pablo Musacchio"
        },
        "position": {
          "id": 3,
          "name": "Right Center Back"
        },
        "teammate": false
      },
      {
        "location": [
          111.1,
          49.0
        ],
        "player": {
          "id": 6762,
          "name": "\u00c1lvaro Gonz\u00e1lez Sober\u00f3n"
        },
        "position": {
          "id": 5,
          "name": "Left Center Back"
        },
        "teammate": false
      },
      {
        "location": [
          118.2,
          43.5
        ],
        "player": {
          "id": 8697,
          "name": "Andr\u00e9s Eduardo Fern\u00e1ndez Moreno"
        },
        "position": {
          "id": 1,
          "name": "Goalkeeper"
        },
        "teammate": false
      }
    ]
  }
}