{
  "id": "95297c1f-4125-4da3-938b-533d69cd59bb",
  "index": 2502,
  "period": 2,
  "timestamp": "00:08:32.145",
  "minute": 53,
  "second": 32,
  "type": {
    "id": 16,
    "name": "Shot"
  },
  "possession": 116,
  "possession_team": {
    "id": 217,
    "name": "Barcelona"
  },
  "play_pattern": {
    "id": 1,
    "name": "Regular Play"
  },
  "team": {
    "id": 217,
    "name": "Barcelona"
  },
  "player": {
    "id": 5487,
    "name": "Antoine Griezmann"
  },
  "position": {
    "id": 21,
    "name": "Left Wing"
  },
  "location": [
    109.1,
    28.4
  ],
  "duration": 0.185206,
  "related_events": [
    "6c3edcd5-36d0-400d-9913-d4c48676679e"
  ],
  "shot": {
    "statsbomb_xg": 0.20364721,
    "end_location": [
      111.8,
      30.7,
      1.3
    ],
    "key_pass_id": "8f2d379b-4ea4-46d0-a600-96e5d365167f",
    "technique": {
      "id": 91,
      "name": "Half Volley"
    },
    "body_part": {
      "id": 38,
      "name": "Left Foot"
    },
    "type": {
      "id": 87,
      "name": "Open Play"
    },
    "outcome": {
      "id": 100,
      "name": "Saved"
    },
    "freeze_frame": [
      {
        "location": [
          110.5,
          46.1
        ],
        "player": {
          "id": 8206,
          "name": "Arturo Erasmo Vidal Pardo"
        },
        "position": {
          "id": 15,
          "name": "Left Center Midfield"
        },
        "teammate": true
      },
      {
        "location": [
          103.9,
          38.8
        ],
        "player": {
          "id": 5246,
          "name": "Luis Alberto Su\u00e1rez D\u00edaz"
        },
        "position": {
          "id": 23,
          "name": "Center Forward"
        },
        "teammate": true
      },
      {
        "location": [
          96.4,
          25.2
        ],
        "player": {
          "id": 5211,
          "name": "Jordi Alba Ramos"
        },
        "position": {
          "id": 6,
          "name": "Left Back"
        },
        "teammate": true
      },
      {
        "location": [
          104.7,
          41.7
        ],
        "player": {
          "id": 5503,
          "name": "Lionel Andr\u00e9s Messi Cuccittini"
        },
        "position": {
          "id": 17,
          "name": "Right Wing"
        },
        "teammate": true
      },
      {
        "location": [
          100.4,
          59.4
        ],
        "player": {
          "id": 6374,
          "name": "N\u00e9lson Cabral Semedo"
        },
        "position": {
          "id": 2,
          "name": "Right Back"
        },
        "teammate": true
      },
      {
        "location": [
          112.1,
          39.5
        ],
        "player": {
          "id": 6397,
          "name": "Unai N\u00fa\u00f1ez Gestoso"
        },
        "position": {
          "id": 3,
          "name": "Right Center Back"
        },
        "teammate": false
      },
      {
        "location": [
          108.7,
          34.9
        ],
        "player": {
          "id": 6649,
          "name": "\u00d3scar de Marcos Arana"
        },
        "position": {
          "id": 2,
          "name": "Right Back"
        },
        "teammate": false
      },
      {
        "location": [
          103.8,
          32.9
        ],
        "player": {
          "id": 6392,
          "name": "\u00cd\u00f1igo Lekue Mart\u00ednez"
        },
        "position": {
          "id": 17,
          "name": "Right Wing"
        },
        "teammate": false
      },
      {
        "location": [
          101.5,
          40.4
        ],
        "player": {
          "id": 11746,
          "name": "Unai L\u00f3pez Cabrera"
        },
        "position": {
          "id": 9,
          "name": "Right Defensive Midfield"
        },
        "teammate": false
      },
      {
        "location": [
          111.9,
          47.2
        ],
        "player": {
          "id": 6789,
          "name": "Mikel Balenziaga Oruesagasti"
        },
        "position": {
          "id": 6,
          "name": "Left Back"
        },
        "teammate": false
      },
      {
        "location": [
          104.3,
          42.9
        ],
        "player": {
          "id": 6877,
          "name": "Yeray \u00c1lvarez L\u00f3pez"
        },
        "position": {
          "id": 5,
          "name": "Left Center Back"
        },
        "teammate": false
      },
      {
        "location": [
          112.3,
          30.9
        ],
        "player": {
          "id": 11748,
          "name": "Unai Sim\u00f3n Mendibil"
        },
        "position": {
          "id": 1,
          "name": "Goalkeeper"
        },
        "teammate": false
      }
    ]
  }
}