{
  "id": "af2f0e18-ed1d-4810-90b4-df6ba647db94",
  "index": 1767,
  "period": 1,
  "timestamp": "00:43:19.375",
  "minute": 43,
  "second": 19,
  "type": {
    "id": 16,
    "name": "Shot"
  },
  "possession": 100,
  "possession_team": {
    "id": 217,
    "name": "Barcelona"
  },
  "play_pattern": {
    "id": 3,
    "name": "From Free Kick"
  },
  "team": {
    "id": 217,
    "name": "Barcelona"
  },
  "player": {
    "id": 5213,
    "name": "Gerard Piqu\u00e9 Bernab\u00e9u"
  },
  "position": {
    "id": 3,
    "name": "Right Center Back"
  },
  "location": [
    118.5,
    43.4
  ],
  "duration": 0.571026,
  "related_events": [
    "7ddf7ba5-63de-4097-ba36-caede96ca8c9"
  ],
  "shot": {
    "open_goal": true,
    "statsbomb_xg": 0.8310603,
    "end_location": [
      120.0,
      45.1
    ],
    "type": {
      "id": 87,
      "name": "Open Play"
    },
    "outcome": {
      "id": 101,
      "name": "Wayward"
    },
    "first_time": true,
    "technique": {
      "id": 95,
      "name": "Volley"
    },
    "body_part": {
      "id": 40,
      "name": "Right Foot"
    },
    "freeze_frame": [
      {
        "location": [
          102.2,
          60.5
        ],
        "player": {
          "id": 5477,
          "name": "Ousmane Demb\u00e9l\u00e9"
        },
        "position": {
          "id": 17,
          "name": "Right Wing"
        },
        "teammate": true
      },
      {
        "location": [
          119.5,
          37.8
        ],
        "player": {
          "id": 6823,
          "name": "Sergio Rico Gonz\u00e1lez"
        },
        "position": {
          "id": 1,
          "name": "Goalkeeper"
        },
        "teammate": false
      },
      {
        "location": [
          113.3,
          46.0
        ],
        "player": {
          "id": 6718,
          "name": "Sergio Escudero Palomo"
        },
        "position": {
          "id": 6,
          "name": "Left Back"
        },
        "teammate": false
      },
      {
        "location": [
          117.2,
          34.8
        ],
        "player": {
          "id": 3501,
          "name": "Philippe Coutinho Correia"
        },
        "position": {
          "id": 21,
          "name": "Left Wing"
        },
        "teammate": true
      },
      {
        "location": [
          111.7,
          39.8
        ],
        "player": {
          "id": 5542,
          "name": "Jos\u00e9 Paulo Bezzera Maciel J\u00fanior"
        },
        "position": {
          "id": 13,
          "name": "Right Center Midfield"
        },
        "teammate": true
      },
      {
        "location": [
          116.9,
          33.1
        ],
        "player": {
          "id": 5246,
          "name": "Luis Alberto Su\u00e1rez D\u00edaz"
        },
        "position": {
          "id": 23,
          "name": "Center Forward"
        },
        "teammate": true
      },
      {
        "location": [
          116.8,
          21.7
        ],
        "player": {
          "id": 5492,
          "name": "Samuel Yves Umtiti"
        },
        "position": {
          "id": 5,
          "name": "Left Center Back"
        },
        "teammate": true
      },
      {
        "location": [
          97.7,
          39.3
        ],
        "player": {
          "id": 5504,
          "name": "\u00c9ver Maximiliano David Banega"
        },
        "position": {
          "id": 11,
          "name": "Left Defensive Midfield"
        },
        "teammate": false
      },
      {
        "location": [
          116.8,
          31.2
        ],
        "player": {
          "id": 5742,
          "name": "Gabriel Iv\u00e1n Mercado"
        },
        "position": {
          "id": 2,
          "name": "Right Back"
        },
        "teammate": false
      },
      {
        "location": [
          119.9,
          27.6
        ],
        "player": {
          "id": 6821,
          "name": "Jes\u00fas Navas Gonz\u00e1lez"
        },
        "position": {
          "id": 12,
          "name": "Right Midfield"
        },
        "teammate": false
      },
      {
        "location": [
          118.7,
          38.8
        ],
        "player": {
          "id": 5534,
          "name": "Simon Thorup Kj\u00e6r"
        },
        "position": {
          "id": 3,
          "name": "Right Center Back"
        },
        "teammate": false
      },
      {
        "location": [
          116.9,
          42.1
        ],
        "player": {
          "id": 6826,
          "name": "Cl\u00e9ment Lenglet"
        },
        "position": {
          "id": 5,
          "name": "Left Center Back"
        },
        "teammate": false
      }
    ]
  }
}